etl_entities/VERSION
etl_entities/__init__.py
etl_entities/entity.py
etl_entities/py.typed
etl_entities/version.py
etl_entities/hwm/__init__.py
etl_entities/hwm/hwm.py
etl_entities/hwm/hwm_type_registry.py
etl_entities/hwm/column/__init__.py
etl_entities/hwm/column/column_hwm.py
etl_entities/hwm/column/date_hwm.py
etl_entities/hwm/column/datetime_hwm.py
etl_entities/hwm/column/int_hwm.py
etl_entities/hwm/file/__init__.py
etl_entities/hwm/file/file_hwm.py
etl_entities/hwm/file/file_list_hwm.py
etl_entities/hwm/file/file_mtime_hwm.py
etl_entities/hwm/key_value/__init__.py
etl_entities/hwm/key_value/key_value_hwm.py
etl_entities/hwm/key_value/key_value_int_hwm.py
etl_entities/hwm_store/__init__.py
etl_entities/hwm_store/base_hwm_store.py
etl_entities/hwm_store/hwm_store_class_registry.py
etl_entities/hwm_store/hwm_store_detect.py
etl_entities/hwm_store/hwm_store_stack_manager.py
etl_entities/hwm_store/memory_hwm_store.py
etl_entities/instance/__init__.py
etl_entities/instance/cluster/__init__.py
etl_entities/instance/cluster/cluster.py
etl_entities/instance/host/__init__.py
etl_entities/instance/host/host.py
etl_entities/instance/path/__init__.py
etl_entities/instance/path/absolute_path.py
etl_entities/instance/path/generic_path.py
etl_entities/instance/path/relative_path.py
etl_entities/instance/url/__init__.py
etl_entities/instance/url/generic_url.py
etl_entities/old_hwm/__init__.py
etl_entities/old_hwm/column_hwm.py
etl_entities/old_hwm/date_hwm.py
etl_entities/old_hwm/datetime_hwm.py
etl_entities/old_hwm/file_hwm.py
etl_entities/old_hwm/file_list_hwm.py
etl_entities/old_hwm/hwm.py
etl_entities/old_hwm/int_hwm.py
etl_entities/plugins/__init__.py
etl_entities/plugins/import_plugins.py
etl_entities/process/__init__.py
etl_entities/process/process.py
etl_entities/process/process_stack_manager.py
etl_entities/source/__init__.py
etl_entities/source/db/__init__.py
etl_entities/source/db/column.py
etl_entities/source/db/table.py
etl_entities/source/file/__init__.py
etl_entities-2.6.0.dist-info/LICENSE.txt
etl_entities-2.6.0.dist-info/METADATA
etl_entities-2.6.0.dist-info/WHEEL
etl_entities-2.6.0.dist-info/entry_points.txt
etl_entities-2.6.0.dist-info/top_level.txt
etl_entities-2.6.0.dist-info/RECORD
