Metadata-Version: 2.2
Name: etl-entities
Version: 2.6.0
Summary: ETL Entities lib for onETL
Home-page: https://github.com/MobileTeleSystems/etl-entities
Author: DataOps.ETL
Author-email: onetools@mts.ru
License: Apache-2.0
Project-URL: Documentation, https://etl-entities.readthedocs.io/
Project-URL: Source, https://github.com/MobileTeleSystems/etl-entities
Project-URL: CI/CD, https://github.com/MobileTeleSystems/etl-entities/actions
Project-URL: Tracker, https://github.com/MobileTeleSystems/etl-entities/issues
Classifier: Development Status :: 5 - Production/Stable
Classifier: Framework :: Pydantic
Classifier: Framework :: Pydantic :: 1
Classifier: Framework :: Pydantic :: 2
Classifier: Intended Audience :: Developers
Classifier: License :: OSI Approved :: Apache Software License
Classifier: Operating System :: OS Independent
Classifier: Programming Language :: Python :: 3 :: Only
Classifier: Programming Language :: Python :: 3.7
Classifier: Programming Language :: Python :: 3.8
Classifier: Programming Language :: Python :: 3.9
Classifier: Programming Language :: Python :: 3.10
Classifier: Programming Language :: Python :: 3.11
Classifier: Programming Language :: Python :: 3.12
Classifier: Programming Language :: Python :: 3.13
Classifier: Typing :: Typed
Requires-Python: >=3.7
License-File: LICENSE.txt
Requires-Dist: bidict
Requires-Dist: frozendict
Requires-Dist: importlib_metadata>=3.6.0
Requires-Dist: psutil
Requires-Dist: pydantic<3
Requires-Dist: typing-extensions>=4.5.0
Dynamic: author
Dynamic: author-email
Dynamic: classifier
Dynamic: description
Dynamic: description-content-type
Dynamic: home-page
Dynamic: license
Dynamic: project-url
Dynamic: requires-dist
Dynamic: requires-python
Dynamic: summary
